accelbyte_py_sdk/api/basic/__init__.py
accelbyte_py_sdk/api/basic/errors.py
accelbyte_py_sdk/api/basic/models/__init__.py
accelbyte_py_sdk/api/basic/models/add_country_group_request.py
accelbyte_py_sdk/api/basic/models/add_country_group_response.py
accelbyte_py_sdk/api/basic/models/config_create.py
accelbyte_py_sdk/api/basic/models/config_info.py
accelbyte_py_sdk/api/basic/models/config_update.py
accelbyte_py_sdk/api/basic/models/country_group_object.py
accelbyte_py_sdk/api/basic/models/country_object.py
accelbyte_py_sdk/api/basic/models/error_entity.py
accelbyte_py_sdk/api/basic/models/field_validation_error.py
accelbyte_py_sdk/api/basic/models/file_upload_url_info.py
accelbyte_py_sdk/api/basic/models/namespace_context.py
accelbyte_py_sdk/api/basic/models/namespace_create.py
accelbyte_py_sdk/api/basic/models/namespace_info.py
accelbyte_py_sdk/api/basic/models/namespace_publisher_info.py
accelbyte_py_sdk/api/basic/models/namespace_simple_info.py
accelbyte_py_sdk/api/basic/models/namespace_status_update.py
accelbyte_py_sdk/api/basic/models/namespace_update.py
accelbyte_py_sdk/api/basic/models/permission.py
accelbyte_py_sdk/api/basic/models/retrieve_country_group_response.py
accelbyte_py_sdk/api/basic/models/retrieve_time_response.py
accelbyte_py_sdk/api/basic/models/update_country_group_request.py
accelbyte_py_sdk/api/basic/models/user_profile_admin.py
accelbyte_py_sdk/api/basic/models/user_profile_bulk_request.py
accelbyte_py_sdk/api/basic/models/user_profile_create.py
accelbyte_py_sdk/api/basic/models/user_profile_info.py
accelbyte_py_sdk/api/basic/models/user_profile_private_create.py
accelbyte_py_sdk/api/basic/models/user_profile_private_info.py
accelbyte_py_sdk/api/basic/models/user_profile_public_info.py
accelbyte_py_sdk/api/basic/models/user_profile_status_update.py
accelbyte_py_sdk/api/basic/models/user_profile_update.py
accelbyte_py_sdk/api/basic/models/user_zip_code.py
accelbyte_py_sdk/api/basic/models/user_zip_code_update.py
accelbyte_py_sdk_service_basic-0.24.0.dist-info/METADATA
accelbyte_py_sdk_service_basic-0.24.0.dist-info/WHEEL
accelbyte_py_sdk_service_basic-0.24.0.dist-info/top_level.txt
accelbyte_py_sdk_service_basic-0.24.0.dist-info/RECORD
